azure/mgmt/app/__init__.py
azure/mgmt/app/_configuration.py
azure/mgmt/app/_container_apps_api_client.py
azure/mgmt/app/_patch.py
azure/mgmt/app/_vendor.py
azure/mgmt/app/_version.py
azure/mgmt/app/aio/__init__.py
azure/mgmt/app/aio/_configuration.py
azure/mgmt/app/aio/_container_apps_api_client.py
azure/mgmt/app/aio/_patch.py
azure/mgmt/app/aio/operations/__init__.py
azure/mgmt/app/aio/operations/_certificates_operations.py
azure/mgmt/app/aio/operations/_container_apps_auth_configs_operations.py
azure/mgmt/app/aio/operations/_container_apps_operations.py
azure/mgmt/app/aio/operations/_container_apps_revision_replicas_operations.py
azure/mgmt/app/aio/operations/_container_apps_revisions_operations.py
azure/mgmt/app/aio/operations/_container_apps_source_controls_operations.py
azure/mgmt/app/aio/operations/_dapr_components_operations.py
azure/mgmt/app/aio/operations/_managed_environments_operations.py
azure/mgmt/app/aio/operations/_managed_environments_storages_operations.py
azure/mgmt/app/aio/operations/_operations.py
azure/mgmt/app/models/__init__.py
azure/mgmt/app/models/_container_apps_api_client_enums.py
azure/mgmt/app/models/_models_py3.py
azure/mgmt/app/operations/__init__.py
azure/mgmt/app/operations/_certificates_operations.py
azure/mgmt/app/operations/_container_apps_auth_configs_operations.py
azure/mgmt/app/operations/_container_apps_operations.py
azure/mgmt/app/operations/_container_apps_revision_replicas_operations.py
azure/mgmt/app/operations/_container_apps_revisions_operations.py
azure/mgmt/app/operations/_container_apps_source_controls_operations.py
azure/mgmt/app/operations/_dapr_components_operations.py
azure/mgmt/app/operations/_managed_environments_operations.py
azure/mgmt/app/operations/_managed_environments_storages_operations.py
azure/mgmt/app/operations/_operations.py
azure_mgmt_app-1.0.0b2.dist-info/LICENSE
azure_mgmt_app-1.0.0b2.dist-info/METADATA
azure_mgmt_app-1.0.0b2.dist-info/WHEEL
azure_mgmt_app-1.0.0b2.dist-info/top_level.txt
azure_mgmt_app-1.0.0b2.dist-info/RECORD
